pyumlgen/__init__.py
pyumlgen/analysis.py
pyumlgen-1.0.0.dist-info/DESCRIPTION.rst
pyumlgen-1.0.0.dist-info/METADATA
pyumlgen-1.0.0.dist-info/RECORD
pyumlgen-1.0.0.dist-info/WHEEL
pyumlgen-1.0.0.dist-info/entry_points.txt
pyumlgen-1.0.0.dist-info/metadata.json
pyumlgen-1.0.0.dist-info/top_level.txt
