Metadata-Version: 2.0
Name: pyumlgen
Version: 1.0.0
Summary: Generate UML diagrams with type information from python modules
Home-page: UNKNOWN
Author: ben simms
Author-email: UNKNOWN
License: UNKNOWN
Platform: UNKNOWN
